[{"from":0,"to":1,"weight":1},{"from":0,"to":2,"weight":8},{"from":2,"to":3,"weight":6},{"from":0,"to":3,"weight":10},{"from":0,"to":4,"weight":1},{"from":0,"to":5,"weight":1},{"from":0,"to":6,"weight":1},{"from":0,"to":7,"weight":1},{"from":0,"to":8,"weight":2},{"from":0,"to":9,"weight":1},{"from":10,"to":11,"weight":1},{"from":3,"to":11,"weight":3},{"from":2,"to":11,"weight":3},{"from":0,"to":11,"weight":5},{"from":11,"to":12,"weight":1},{"from":11,"to":13,"weight":1},{"from":11,"to":14,"weight":1},{"from":11,"to":15,"weight":1},{"from":16,"to":17,"weight":4},{"from":17,"to":18,"weight":4},{"from":16,"to":18,"weight":4},{"from":18,"to":19,"weight":4},{"from":17,"to":19,"weight":4},{"from":16,"to":19,"weight":4},{"from":19,"to":20,"weight":4},{"from":18,"to":20,"weight":3},{"from":17,"to":20,"weight":3},{"from":16,"to":20,"weight":3},{"from":18,"to":21,"weight":3},{"from":20,"to":21,"weight":5},{"from":19,"to":21,"weight":3},{"from":17,"to":21,"weight":3},{"from":16,"to":21,"weight":3},{"from":21,"to":22,"weight":4},{"from":20,"to":22,"weight":4},{"from":18,"to":22,"weight":3},{"from":19,"to":22,"weight":3},{"from":17,"to":22,"weight":3},{"from":16,"to":22,"weight":3},{"from":21,"to":23,"weight":4},{"from":20,"to":23,"weight":4},{"from":22,"to":23,"weight":4},{"from":18,"to":23,"weight":3},{"from":19,"to":23,"weight":3},{"from":17,"to":23,"weight":3},{"from":16,"to":23,"weight":3},{"from":12,"to":23,"weight":2},{"from":11,"to":23,"weight":9},{"from":23,"to":24,"weight":2},{"from":11,"to":24,"weight":7},{"from":24,"to":25,"weight":13},{"from":23,"to":25,"weight":1},{"from":11,"to":25,"weight":12},{"from":25,"to":26,"weight":1},{"from":24,"to":26,"weight":4},{"from":16,"to":26,"weight":1},{"from":11,"to":26,"weight":31},{"from":26,"to":27,"weight":1},{"from":25,"to":27,"weight":5},{"from":24,"to":27,"weight":1},{"from":23,"to":27,"weight":5},{"from":11,"to":27,"weight":17},{"from":27,"to":28,"weight":1},{"from":11,"to":28,"weight":8},{"from":27,"to":29,"weight":1},{"from":23,"to":29,"weight":1},{"from":11,"to":29,"weight":2},{"from":23,"to":30,"weight":1},{"from":30,"to":31,"weight":2},{"from":27,"to":31,"weight":1},{"from":23,"to":31,"weight":2},{"from":11,"to":31,"weight":3},{"from":11,"to":32,"weight":1},{"from":27,"to":33,"weight":1},{"from":11,"to":33,"weight":2},{"from":29,"to":34,"weight":2},{"from":11,"to":34,"weight":3},{"from":34,"to":35,"weight":3},{"from":29,"to":35,"weight":2},{"from":11,"to":35,"weight":3},{"from":34,"to":36,"weight":2},{"from":29,"to":36,"weight":1},{"from":35,"to":36,"weight":2},{"from":11,"to":36,"weight":2},{"from":34,"to":37,"weight":2},{"from":29,"to":37,"weight":1},{"from":36,"to":37,"weight":2},{"from":35,"to":37,"weight":2},{"from":11,"to":37,"weight":2},{"from":34,"to":38,"weight":2},{"from":29,"to":38,"weight":1},{"from":36,"to":38,"weight":2},{"from":37,"to":38,"weight":2},{"from":35,"to":38,"weight":2},{"from":11,"to":38,"weight":2},{"from":25,"to":39,"weight":1},{"from":25,"to":40,"weight":1},{"from":25,"to":41,"weight":3},{"from":24,"to":41,"weight":2},{"from":41,"to":42,"weight":2},{"from":25,"to":42,"weight":2},{"from":24,"to":42,"weight":1},{"from":27,"to":43,"weight":1},{"from":26,"to":43,"weight":1},{"from":11,"to":43,"weight":3},{"from":28,"to":44,"weight":3},{"from":11,"to":44,"weight":1},{"from":28,"to":45,"weight":2},{"from":46,"to":47,"weight":1},{"from":47,"to":48,"weight":2},{"from":27,"to":48,"weight":1},{"from":25,"to":48,"weight":1},{"from":11,"to":48,"weight":1},{"from":26,"to":49,"weight":3},{"from":11,"to":49,"weight":2},{"from":49,"to":50,"weight":1},{"from":24,"to":50,"weight":1},{"from":49,"to":51,"weight":9},{"from":26,"to":51,"weight":2},{"from":11,"to":51,"weight":2},{"from":51,"to":52,"weight":1},{"from":39,"to":52,"weight":1},{"from":51,"to":53,"weight":1},{"from":51,"to":54,"weight":2},{"from":49,"to":54,"weight":1},{"from":26,"to":54,"weight":1},{"from":51,"to":55,"weight":6},{"from":54,"to":55,"weight":1},{"from":49,"to":55,"weight":12},{"from":41,"to":55,"weight":5},{"from":48,"to":55,"weight":4},{"from":39,"to":55,"weight":1},{"from":26,"to":55,"weight":21},{"from":25,"to":55,"weight":2},{"from":16,"to":55,"weight":1},{"from":11,"to":55,"weight":19},{"from":55,"to":56,"weight":1},{"from":49,"to":56,"weight":1},{"from":55,"to":57,"weight":1},{"from":41,"to":57,"weight":1},{"from":48,"to":57,"weight":1},{"from":57,"to":58,"weight":1},{"from":55,"to":58,"weight":7},{"from":48,"to":58,"weight":7},{"from":27,"to":58,"weight":6},{"from":11,"to":58,"weight":4},{"from":57,"to":59,"weight":2},{"from":58,"to":59,"weight":15},{"from":55,"to":59,"weight":5},{"from":48,"to":59,"weight":6},{"from":59,"to":60,"weight":2},{"from":58,"to":60,"weight":4},{"from":48,"to":60,"weight":1},{"from":59,"to":61,"weight":5},{"from":60,"to":61,"weight":2},{"from":57,"to":61,"weight":1},{"from":58,"to":61,"weight":6},{"from":55,"to":61,"weight":1},{"from":48,"to":61,"weight":2},{"from":59,"to":62,"weight":13},{"from":60,"to":62,"weight":3},{"from":61,"to":62,"weight":6},{"from":57,"to":62,"weight":2},{"from":58,"to":62,"weight":17},{"from":55,"to":62,"weight":9},{"from":48,"to":62,"weight":7},{"from":41,"to":62,"weight":1},{"from":61,"to":63,"weight":3},{"from":62,"to":63,"weight":6},{"from":59,"to":63,"weight":5},{"from":60,"to":63,"weight":2},{"from":57,"to":63,"weight":2},{"from":58,"to":63,"weight":4},{"from":55,"to":63,"weight":1},{"from":48,"to":63,"weight":5},{"from":61,"to":64,"weight":6},{"from":62,"to":64,"weight":12},{"from":63,"to":64,"weight":4},{"from":59,"to":64,"weight":9},{"from":60,"to":64,"weight":2},{"from":57,"to":64,"weight":1},{"from":58,"to":64,"weight":10},{"from":55,"to":64,"weight":5},{"from":48,"to":64,"weight":5},{"from":11,"to":64,"weight":1},{"from":61,"to":65,"weight":5},{"from":62,"to":65,"weight":5},{"from":63,"to":65,"weight":5},{"from":64,"to":65,"weight":7},{"from":59,"to":65,"weight":5},{"from":60,"to":65,"weight":2},{"from":57,"to":65,"weight":1},{"from":58,"to":65,"weight":5},{"from":55,"to":65,"weight":2},{"from":48,"to":65,"weight":3},{"from":65,"to":66,"weight":2},{"from":61,"to":66,"weight":1},{"from":62,"to":66,"weight":2},{"from":63,"to":66,"weight":1},{"from":64,"to":66,"weight":3},{"from":59,"to":66,"weight":1},{"from":60,"to":66,"weight":1},{"from":58,"to":66,"weight":3},{"from":48,"to":66,"weight":1},{"from":57,"to":67,"weight":3},{"from":48,"to":68,"weight":1},{"from":41,"to":68,"weight":1},{"from":27,"to":68,"weight":1},{"from":25,"to":68,"weight":5},{"from":24,"to":68,"weight":1},{"from":11,"to":68,"weight":1},{"from":68,"to":69,"weight":6},{"from":48,"to":69,"weight":1},{"from":41,"to":69,"weight":1},{"from":27,"to":69,"weight":2},{"from":25,"to":69,"weight":6},{"from":24,"to":69,"weight":1},{"from":11,"to":69,"weight":1},{"from":68,"to":70,"weight":4},{"from":69,"to":70,"weight":4},{"from":58,"to":70,"weight":1},{"from":41,"to":70,"weight":1},{"from":27,"to":70,"weight":1},{"from":25,"to":70,"weight":4},{"from":24,"to":70,"weight":1},{"from":11,"to":70,"weight":1},{"from":68,"to":71,"weight":2},{"from":69,"to":71,"weight":2},{"from":70,"to":71,"weight":2},{"from":48,"to":71,"weight":1},{"from":41,"to":71,"weight":1},{"from":27,"to":71,"weight":1},{"from":25,"to":71,"weight":1},{"from":11,"to":71,"weight":1},{"from":27,"to":72,"weight":1},{"from":26,"to":72,"weight":2},{"from":11,"to":72,"weight":1},{"from":48,"to":73,"weight":2},{"from":73,"to":74,"weight":3},{"from":48,"to":74,"weight":2},{"from":68,"to":75,"weight":3},{"from":69,"to":75,"weight":3},{"from":70,"to":75,"weight":1},{"from":71,"to":75,"weight":1},{"from":48,"to":75,"weight":1},{"from":41,"to":75,"weight":1},{"from":25,"to":75,"weight":3},{"from":65,"to":76,"weight":1},{"from":66,"to":76,"weight":1},{"from":62,"to":76,"weight":1},{"from":63,"to":76,"weight":1},{"from":64,"to":76,"weight":1},{"from":58,"to":76,"weight":1},{"from":48,"to":76,"weight":1}]